{
    "$help": "https://aka.ms/terminal-documentation",
    "$schema": "https://aka.ms/terminal-profiles-schema",
    "actions": [
        {
            "command": {
                "action": "copy",
                "singleLine": false
            },
            "id": "User.copy.644BA8F2",
            "keys": "ctrl+c"
        },
        {
            "command": "paste",
            "id": "User.paste",
            "keys": "ctrl+v"
        },
        {
            "command": "find",
            "id": "User.find",
            "keys": "ctrl+shift+f"
        },
        {
            "command": {
                "action": "splitPane",
                "split": "auto",
                "splitMode": "duplicate"
            },
            "id": "User.splitPane.A6751878",
            "keys": "alt+shift+d"
        }
    ],
    "copyFormatting": "none",
    "copyOnSelect": false,
    "defaultProfile": "{51855cb2-8cce-5362-8f54-464b92b32386}",
    "newTabMenu": [
        {
            "type": "remainingProfiles"
        }
    ],
    "profiles": {
        "defaults": {
            "opacity": 65,
            "useAcrylic": false
        },
        "list": [
            {
                "commandline": "%SystemRoot%\\System32\\WindowsPowerShell\\v1.0\\powershell.exe",
                "guid": "{61c54bbd-c2c6-5271-96e7-009a87ff44bf}",
                "hidden": false,
                "name": "Windows PowerShell"
            },
            {
                "commandline": "%SystemRoot%\\System32\\cmd.exe",
                "guid": "{0caa0dad-35be-5f56-a8ff-afceeeaa6101}",
                "hidden": false,
                "colorScheme": "Tuni",
                "name": "Command Prompt"
            },
            {
                "guid": "{b453ae62-4e3d-5e58-b989-0a998ec441b8}",
                "hidden": false,
                "name": "Azure Cloud Shell",
                "source": "Windows.Terminal.Azure"
            },
            {
                "colorScheme": "Tuni",
                "font": {
                    "face": "Hack Nerd Font",
                    "size": 11
                },
                "guid": "{51855cb2-8cce-5362-8f54-464b92b32386}",
                "hidden": false,
                "name": "Ubuntu",
                "opacity": 90,
                "source": "CanonicalGroupLimited.Ubuntu_79rhkp1fndgsc",
                "useAcrylic": false
            },
            {
                "guid": "{2c4de342-38b7-51cf-b940-2309a097f518}",
                "hidden": true,
                "name": "Ubuntu",
                "source": "Windows.Terminal.Wsl"
            }
        ]
    },
    "schemes": [
        {
            "name": "Tuni",
            "cursorColor": "#a09090",
            "selectionBackground": "#a09090",
            "background": "#15191e",
            "foreground": "#dbdbdb",
            "black": "#0C0C0C",
            "blue": "#557beb",
            "cyan": "#3A96DD",
            "green": "#13A10E",
            "purple": "#881798",
            "red": "#C50F1F",
            "white": "#CCCCCC",
            "yellow": "#C19C00",
            "brightBlack": "#767676",
            "brightBlue": "#3B78FF",
            "brightCyan": "#61D6D6",
            "brightGreen": "#16C60C",
            "brightPurple": "#B4009E",
            "brightRed": "#E74856",
            "brightWhite": "#F2F2F2",
            "brightYellow": "#F9F1A5"
        },
    ],
    "startOnUserLogin": true,
    "themes": []
}
